<meta>
	<infos name="The Sims MTA World" author="FatalTerror" version="2.0" type="script"></infos>

	<!-- Client -->
	<script src="client/main.lua" type="client"/>
	<script src="client/town.lua" type="client"/>

	<!-- Server -->
	<script src="server/main.lua" type="server"/>
	<script src="server/town.lua" type="server"/>
	
	<!-- Files -->
	<file src="models/corner_long.col"></file>
	<file src="models/corner_long.dff"></file>
	<file src="models/corner_short.col"></file>
	<file src="models/corner_short.dff"></file>
	<file src="models/cross_junction.col"></file>
	<file src="models/cross_junction.dff"></file>
	<file src="models/roads_texture.txd"></file>
	<file src="models/straight_road.col"></file>
	<file src="models/straight_road.dff"></file>
	<file src="models/t_junction.col"></file>
	<file src="models/t_junction.dff"></file>
	<file src="models/grass.col"></file>
	<file src="models/grass.dff"></file>

	<!-- Export functions -->
	<export function="TownInit" type="client"></export>

</meta>